shard_client/__init__.py
shard_client/scanner.py
shard_client/lib/color_printer.py
shard_client/lib/logclass.py
shard_client/lib/mqlib.py
shard_client/lib/mqtt_queue.py
shard_client/lib/status.py
shard_client-0.0.5.dist-info/METADATA
shard_client-0.0.5.dist-info/WHEEL
shard_client-0.0.5.dist-info/top_level.txt
shard_client-0.0.5.dist-info/RECORD
