Metadata-Version: 2.1
Name: shard-client
Version: 0.0.5
Summary: A modification for axiom scanner
Author-email: HeWhoMustNotBeNamed <hewhomustnotbenamed23@proton.me>
Classifier: Programming Language :: Python :: 3
Classifier: License :: OSI Approved :: MIT License
Classifier: Operating System :: OS Independent
Requires-Python: >=3.7
Requires-Dist: python-dotenv
Requires-Dist: aiofiles
Requires-Dist: colored
Requires-Dist: gmqtt
